lightcards/__init__.py
lightcards/deck.py
lightcards/display.py
lightcards/lightcards.py
lightcards/parse.py
lightcards/progress.py
lightcards-0.5.0.data/data/man/man1/lightcards.1
lightcards-0.5.0.data/scripts/lightcards
lightcards-0.5.0.dist-info/LICENSE
lightcards-0.5.0.dist-info/METADATA
lightcards-0.5.0.dist-info/WHEEL
lightcards-0.5.0.dist-info/top_level.txt
lightcards-0.5.0.dist-info/RECORD
