Metadata-Version: 2.1
Name: lightcards
Version: 0.5.0
Summary: Terminal flashcards from Markdown
Home-page: https://sr.ht/~armaan/lightcards
Author: Armaan Bhojwani
Author-email: me@armaanb.net
License: MIT
Platform: UNKNOWN
Classifier: Development Status :: 4 - Beta
Classifier: Intended Audience :: Other Audience
Classifier: Environment :: Console :: Curses
Classifier: License :: OSI Approved :: MIT License
Classifier: Topic :: Utilities
Requires-Dist: beautifulsoup4
Requires-Dist: markdown
